{
    "guest": {
        "A01": {
            "des": {
                "it": "Benvenuto",
                "en": "Wellcome",
                "fr": "",
                "es": ""
            },
            "icon": "",
            "list": [
                "Pi_Login"
            ],
            "hidden": 1
        }
    },
    "root": {
   		"A01": {
            "des": {
                "it": "Sistema",
                "en": "System",
                "fr": "",
                "es": ""
            },
            "icon": "",
            "list": [
                "Pi_Login",
                "Pi_Settings",
                "Pi_Qry",
                "test",
                "Pi_DB_Utility",
                "Pi_Info",
                "Pi_I18n"
            ],
            "hidden": 0
        }
    }
}